{
    "status": "ok",
    "totalResults": 43,
    "articles": [
        {
            "source": {
                "id": "espn",
                "name": "ESPN"
            },
            "author": "ESPN",
            "title": "CFP rankings release: See the penultimate top 25 and bracket - ESPN",
            "description": "A look at the new bracket based on the College Football Playoff committee's fifth set of rankings.",
            "url": "https://www.espn.com/college-football/story/_/id/47180433/college-football-playoff-2025-byes-bracket-new-top-25",
            "urlToImage": "https://a4.espncdn.com/combiner/i?img=%2Fphoto%2F2025%2F1202%2FWeek15_16x9.png",
            "publishedAt": "2025-12-03T00:10:00Z",
            "content": "The College Football Playoff committee released its penultimate set of rankings Tuesday, and Ohio State remains at the top.\r\nThe committee has released its rankings each Tuesday for the past five wee… [+1478 chars]"
        },
        {
            "source": {
                "id": "espn",
                "name": "ESPN"
            },
            "author": "Stephen Holder",
            "title": "Colts make change at kicker but pass on Tucker - ESPN",
            "description": "The Colts waived kicker Michael Badgley on Tuesday, then signed former Saints kicker Blake Grupe to their practice squad after a tryout that included former Ravens great Justin Tucker.",
            "url": "https://www.espn.com/nfl/story/_/id/47181223/colts-waive-kicker-michael-badgley-sign-blake-grupe",
            "urlToImage": "https://a3.espncdn.com/combiner/i?img=%2Fphoto%2F2025%2F1202%2Fr1583994_1296x729_16%2D9.jpg",
            "publishedAt": "2025-12-02T22:44:00Z",
            "content": "NDIANAPOLIS -- The Colts have reversed course at kicker.\r\nIndianapolis waived Michael Badgley on Tuesday, then signed former New Orleans Saints kicker Blake Grupe to their practice squad after a tryo… [+1278 chars]"
        },
        {
            "source": {
                "id": "politico",
                "name": "Politico"
            },
            "author": "Mia McCarthy, Nick Niedzwiadek, Juan Perez Jr.",
            "title": "College sports bill heads to final vote despite GOP defections - Politico",
            "description": "The 210-209 vote paves the way for House passage as soon as Wednesday.",
            "url": "https://www.politico.com/live-updates/2025/12/02/congress/college-sports-bill-heads-to-final-vote-despite-gop-defections-00673376",
            "urlToImage": "https://www.politico.com/dims4/default/cd84e30/2147483647/resize/1200x/quality/90/?url=https%3A%2F%2Fstatic.politico.com%2F92%2F04%2F297f1002490ea44fcc41f2414060%2Fu-s-congress-31076.jpg",
            "publishedAt": "2025-12-02T22:35:39Z",
            "content": null
        },
        {
            "source": {
                "id": null,
                "name": "Barca Blaugranes"
            },
            "author": "Gill Clark",
            "title": "‘On another level’ - Hansi Flick thrilled by Barcelona’s win over Atletico Madrid - Barca Blaugranes",
            "description": "His side are now four points clear at the top of La Liga.",
            "url": "https://www.barcablaugranes.com/barcelona-la-liga/107181/on-another-level-hansi-flick-thrilled-by-barcelonas-win-over-atletico-madrid",
            "urlToImage": "https://platform.barcablaugranes.com/wp-content/uploads/sites/21/2025/12/gettyimages-2249629522.jpg?quality=90&strip=all&crop=0%2C11.926951522699%2C100%2C76.146096954602&w=1200",
            "publishedAt": "2025-12-02T22:28:34Z",
            "content": "Hansi Flick was a happy man after seeing his Barcelona team beat Atletico Madrid 3-1 at Camp Nou on Tuesday night in La Liga.\r\nThe Barcelona boss cut a dejected figure last time out against Alaves bu… [+1056 chars]"
        },
        {
            "source": {
                "id": null,
                "name": "NBCSports.com"
            },
            "author": "Mike Florio",
            "title": "Mississippi allows Charlie Weis Jr. to return for playoffs, before joining LSU - NBC Sports",
            "description": "Mississippi didn't want to let coach Lane Kiffin stick around for the College Football Playoff.",
            "url": "https://www.nbcsports.com/nfl/profootballtalk/rumor-mill/news/mississippi-allows-charlie-weis-jr-to-return-for-playoffs-before-joining-lsu",
            "urlToImage": "https://nbcsports.brightspotcdn.com/dims4/default/cbf3e02/2147483647/strip/true/crop/3954x2224+0+0/resize/1440x810!/quality/90/?url=https%3A%2F%2Fnbc-sports-production-nbc-sports.s3.us-east-1.amazonaws.com%2Fbrightspot%2F06%2F4b%2F5437b41d47a1af06f56ca9dd2806%2Fhttps-delivery-gettyimages.com%2Fdownloads%2F2182597689",
            "publishedAt": "2025-12-02T22:18:49Z",
            "content": "Mississippi didnt want to let coach Lane Kiffin stick around for the College Football Playoff. However, Ole Miss has decided to let its old offensive coordinator finish the job.\r\nVia Adam Rittenberg … [+1651 chars]"
        },
        {
            "source": {
                "id": null,
                "name": "247Sports"
            },
            "author": "Nathan King",
            "title": "Tracking Alex Golesh's 2026 Auburn coaching staff - 247Sports",
            "description": "Auburns new coach is wasting little time putting together his inaugural staff on the Plains",
            "url": "https://247sports.com/college/auburn/longformarticle/auburn-football-coaching-staff-alex-golesh-dj-durkin-264440447/",
            "urlToImage": "https://s3media.247sports.com/Uploads/Assets/187/464/13464187.jpg?width=1200&height=628&crop=1.91:1&fit=cover",
            "publishedAt": "2025-12-02T22:07:50Z",
            "content": "Auburn's new coach is wasting little time putting together his inaugural staff on the Plains.\r\nAlex Golesh is off an running this week after being hired Sunday, and he obviously has a lengthy to-do l… [+1505 chars]"
        },
        {
            "source": {
                "id": null,
                "name": "NBCSports.com"
            },
            "author": "Mike Florio",
            "title": "Patriots brought hard hitting to Monday night game - NBC Sports",
            "description": "Some great teams tend to play with their food.",
            "url": "https://www.nbcsports.com/nfl/profootballtalk/rumor-mill/news/patriots-brought-hard-hitting-to-monday-night-game",
            "urlToImage": "https://nbcsports.brightspotcdn.com/dims4/default/dbd8f95/2147483647/strip/true/crop/3515x1977+0+0/resize/1440x810!/quality/90/?url=https%3A%2F%2Fnbc-sports-production-nbc-sports.s3.us-east-1.amazonaws.com%2Fbrightspot%2F0b%2F7f%2Fda221f21412792e3b310f14bac02%2Fhttps-delivery-gettyimages.com%2Fdownloads%2F2248968252",
            "publishedAt": "2025-12-02T22:00:43Z",
            "content": "Some great teams tend to play with their food. On Monday night, the Patriots devoured everything on their plate.\r\nIt was obvious from the get-go. The Patriots were hitting hard last night. Early, oft… [+1179 chars]"
        },
        {
            "source": {
                "id": null,
                "name": "NBCSports.com"
            },
            "author": "Myles Simmons",
            "title": "NFL announces times for Eagles-Commanders, Packers-Bears Week 16 Saturday doubleheader - NBC Sports",
            "description": "The NFL has announced kickoff times for the Saturday, Dec. 20 doubleheader featuring the Week 16 matchups between the Eagles and Commanders, along with the Bears and Packers.",
            "url": "https://www.nbcsports.com/nfl/profootballtalk/rumor-mill/news/nfl-announces-times-for-eagles-commanders-packers-bears-week-16-saturday-doubleheader",
            "urlToImage": "https://nbcsports.brightspotcdn.com/dims4/default/4b97580/2147483647/strip/true/crop/2824x1589+0+0/resize/1440x810!/quality/90/?url=https%3A%2F%2Fnbc-sports-production-nbc-sports.s3.us-east-1.amazonaws.com%2Fbrightspot%2Fcd%2F3d%2F447e19ad1207280095461f4bae8b%2Fcd0ymzcznguwzdbhnduynddiytjhm2yyzthlmtjjotqwyyznptbhntg4m2vlymeyyzk3mzc2n2uwnda2nmjjzgi4njk5.jpeg",
            "publishedAt": "2025-12-02T21:35:01Z",
            "content": "The NFL has announced kickoff times for the Saturday, Dec. 20 doubleheader featuring the Week 16 matchups between the Eagles and Commanders, along with the Bears and Packers.\r\nPhiladelphia at Washing… [+578 chars]"
        },
        {
            "source": {
                "id": null,
                "name": "Yahoo Entertainment"
            },
            "author": "Drake Riggs",
            "title": "'I've done a lot for the UFC': Frustrated Tom Aspinall tells all in first interview since Ciryl Gane eye-pokes - Yahoo Sports",
            "description": "The UFC heavyweight champion was brutally honest Tuesday in his first public conversation since UFC 321's ill-fated bout against Ciryl Gane.",
            "url": "https://sports.yahoo.com/mma/article/ive-done-a-lot-for-the-ufc-tom-aspinall-disappointed-in-dana-white-as-potential-eye-surgeries-loom-213224466.html",
            "urlToImage": "https://s.yimg.com/ny/api/res/1.2/SvgB3IMcbpDjGTdx.6stcg--/YXBwaWQ9aGlnaGxhbmRlcjt3PTEyMDA7aD04MDA7Y2Y9d2VicA--/https://s.yimg.com/os/creatr-uploaded-images/2025-12/8f6ed370-cfc4-11f0-bafb-18016d6efeda",
            "publishedAt": "2025-12-02T21:32:24Z",
            "content": "Tom Aspinall may be sidelined longer than expected.\r\nAfter losing a year of his career to circumstances outside the cage, the undisputed UFC heavyweight champion returned to a nightmare scenario agai… [+5632 chars]"
        },
        {
            "source": {
                "id": null,
                "name": "Charlottefootballclub.com"
            },
            "author": "Charlotte Football Club",
            "title": "Charlotte to Host United States Men’s National Team Friendly Ahead of 2026 FIFA World Cup - Charlotte FC",
            "description": "USMNT returns to Charlotte for key friendly match on May 31 in Allstate Continental Clásico",
            "url": "https://www.charlottefootballclub.com/news/charlotte-to-host-united-states-men-s-national-team-friendly-ahead-of-2026-fifa-world-cup",
            "urlToImage": "https://images.mlssoccer.com/image/private/t_editorial_landscape_3_4_desktop/mls-clt/cmkn2ltna6blegcz2xz4.png",
            "publishedAt": "2025-12-02T21:06:29Z",
            "content": null
        },
        {
            "source": {
                "id": null,
                "name": "NBCSports.com"
            },
            "author": "Josh Alper",
            "title": "Joe Schoen: There are pieces in place, I know we’re going to get it right - NBC Sports",
            "description": "When the Giants fired head coach Brian Daboll last month, they announced that General Manager Joe Schoen will lead the search for Daboll's replacement.",
            "url": "https://www.nbcsports.com/nfl/profootballtalk/rumor-mill/news/joe-schoen-there-are-pieces-in-place-i-know-were-going-to-get-it-right",
            "urlToImage": "https://nbcsports.brightspotcdn.com/dims4/default/ce292f1/2147483647/strip/true/crop/6000x3375+0+0/resize/1440x810!/quality/90/?url=https%3A%2F%2Fnbc-sports-production-nbc-sports.s3.us-east-1.amazonaws.com%2Fbrightspot%2Fe1%2F8a%2Fc75a7f9544ae894ae42dfd1e5c2c%2Fhttps-delivery-gettyimages.com%2Fdownloads%2F2201994831",
            "publishedAt": "2025-12-02T20:42:40Z",
            "content": "When the Giants fired head coach Brian Daboll last month, they announced that General Manager Joe Schoen will lead the search for Dabolls replacement. \r\nDaboll and Schoen were both hired in 2022, whi… [+1252 chars]"
        },
        {
            "source": {
                "id": null,
                "name": "BBC News"
            },
            "author": "Katharine Sharpe",
            "title": "Erling Haaland: Who has scored 100 goals in the Premier League? - BBC",
            "description": "Our Ask Me Anything team looks at who is in the Premier League's '100 club' of goalscorers.",
            "url": "https://www.bbc.com/sport/football/articles/cql94xeyv72o",
            "urlToImage": "https://ichef.bbci.co.uk/ace/branded_sport/1200/cpsprodpb/03fd/live/a1729410-ba31-11f0-aa13-0b0479f6f42a.png",
            "publishedAt": "2025-12-02T20:20:37Z",
            "content": "<li>Alan Shearer 260 (Blackburn Rovers 112, Newcastle United 148)\r\n</li><li>Harry Kane* 213 (Tottenham Hotspur 213)\r\n</li><li>Wayne Rooney - 208 (Everton 25, Manchester United 183)\r\n</li><li>Mohamed … [+2612 chars]"
        },
        {
            "source": {
                "id": null,
                "name": "Detroit Free Press"
            },
            "author": "Marlowe Alter",
            "title": "Pat Fitzgerald press conference livestream video at Michigan State - Detroit Free Press",
            "description": "Here's how to watch video of Pat Fitzgerald press conference introducing him as new Michigan State football coach Tuesday afternoon in East Lansing.",
            "url": "https://www.freep.com/story/sports/college/michigan-state/spartans/2025/12/02/pat-fitzgerald-press-conference-livestream-michigan-state/87565738007/",
            "urlToImage": "https://www.freep.com/gcdn/authoring/authoring-images/2025/12/02/PDTF/87571855007-screenshot-20251202-151238.jpg?crop=1028,579,x0,y17&width=1028&height=579&format=pjpg&auto=webp",
            "publishedAt": "2025-12-02T20:14:00Z",
            "content": "The birthday boy is in East Lansing.\r\nThe Pat Fitzgerald press conference Tuesday introducing him as Michigan State football coach has a start time of 3 p.m. ET.\r\nWe have the livestream video of Fitz… [+2738 chars]"
        },
        {
            "source": {
                "id": null,
                "name": "NBCSports.com"
            },
            "author": "Michael David Smith",
            "title": "Joe Schoen defends Abdul Carter: He’s 21 years old and thrust into the spotlight - NBC Sports",
            "description": "\"Abdul is a young man that's 21 years old that's smart and understands the magnitude of his actions and also understands what it means to be a pro,\" Schoen said.",
            "url": "https://www.nbcsports.com/nfl/profootballtalk/rumor-mill/news/joe-schoen-defends-abdul-carter-hes-21-years-old-and-thrust-into-the-spotlight",
            "urlToImage": "https://nbcsports.brightspotcdn.com/dims4/default/8027f55/2147483647/strip/true/crop/3270x1839+0+185/resize/1440x810!/quality/90/?url=https%3A%2F%2Fnbc-sports-production-nbc-sports.s3.us-east-1.amazonaws.com%2Fbrightspot%2Fe9%2F96%2F83ece99d43c88bda280c48b1e9f8%2Fhttps-delivery-gettyimages.com%2Fdownloads%2F2249469959",
            "publishedAt": "2025-12-02T19:57:24Z",
            "content": "Giants General Manager Joe Schoen spent the third overall pick in the 2025 NFL draft on Abdul Carter, a pass rusher who to this point in his career has more benchings than sacks. But Schoen says he r… [+1101 chars]"
        },
        {
            "source": {
                "id": null,
                "name": "Sports Illustrated"
            },
            "author": "Albert Breer",
            "title": "The Patriots Have Taken on Mike Vrabel’s Identity - Sports Illustrated",
            "description": "New England’s first-place team has characteristics of the coach’s old teams in Tennessee. Plus, notes on Abdul Carter, the Cowboys’ offensive line and more.",
            "url": "https://www.si.com/nfl/patriots-taken-mike-vrabel-identity",
            "urlToImage": "https://images2.minutemediacdn.com/image/upload/c_crop,w_5377,h_3024,x_0,y_0/c_fill,w_1440,ar_16:9,f_auto,q_auto,g_auto/images/ImagnImages/mmsport/si/01kbg92tcbyfdc4b0n21.jpg",
            "publishedAt": "2025-12-02T19:45:30Z",
            "content": "Were in December now, and rolling into Week 14 with this weeks Tuesday notes \r\nThere are a lot of things that can be said about the Patriots\r\n coming out of Mondays 3315 rout of the Giants. Many of t… [+11909 chars]"
        },
        {
            "source": {
                "id": null,
                "name": "MLB Trade Rumors"
            },
            "author": "Darragh McDonald",
            "title": "Blue Jays Sign Dylan Cease To Seven-Year Deal - MLB Trade Rumors",
            "description": "December 2nd: The Jays made it official today, announcing they have signed Cease to a seven-year deal. November 26th: The...",
            "url": "https://www.mlbtraderumors.com/2025/12/blue-jays-to-sign-dylan-cease-to-seven-year-deal.html",
            "urlToImage": "https://cdn.mlbtraderumors.com/files/2025/10/USATSI_27120143-1024x683.jpg",
            "publishedAt": "2025-12-02T19:30:03Z",
            "content": "December 2nd: The Jays made it official today, announcing they have signed Cease to a seven-year deal.\r\nNovember 26th: The Blue Jays are making a major splash at the top of the rotation. Toronto is i… [+7348 chars]"
        },
        {
            "source": {
                "id": null,
                "name": "Footballscoop.com"
            },
            "author": "",
            "title": "Broyles Award announces 15 semifinalists - FootballScoop.com",
            "description": "About a week after naming a record amount of nominees for the Broyles Award, the organization has announced their list of 15 semifinalists.The award, which has gone annually to the",
            "url": "https://www.footballscoop.com/2025/12/02/broyles-award-2025-announces-15-semifinalists",
            "urlToImage": "https://www.footballscoop.com/img/random/broyles-award-semifinalists-2025-544x306.jpg",
            "publishedAt": "2025-12-02T19:19:25Z",
            "content": "About a week after naming a record amount of nominees for the Broyles Award, the organization has announced their list of 15 semifinalists.\r\nThe award, which has gone annually to the top assistant co… [+1979 chars]"
        },
        {
            "source": {
                "id": null,
                "name": "Deseret News"
            },
            "author": "Krysyan Edler",
            "title": "BYU: Steve Young weighs in on Kalani Sitake-Penn State rumors - Deseret News",
            "description": "Kalani Sitake-Penn State rumors. Is Kalani Sitake leaving BYU for Penn State? Is Kalani Sitake staying at BYU? Lane Kiffin departure. BYU head coach.",
            "url": "https://www.deseret.com/sports/2025/12/02/steve-young-on-kalani-sitake-penn-state-byu/",
            "urlToImage": "https://www.deseret.com/resizer/v2/ECVRDOXAIZAYFNOJF3EF67NYB4.JPG?focal=0%2C0&auth=8761d93c71b7bd8a9d6caebf5b6a89456366f864e9751f578b1953255e032744&width=630",
            "publishedAt": "2025-12-02T18:51:37Z",
            "content": "Hall of Fame quarterback Steve Young called the departures of coaches leaving mid-season madness while on the Dan Patrick Show Tuesday.\r\nPatrick asked Young how he would have felt if his head coach h… [+2259 chars]"
        },
        {
            "source": {
                "id": null,
                "name": "Eleven Warriors"
            },
            "author": null,
            "title": "Ryan Day Had “An Inkling” Ohio State Might Lose Helmet Communications at Michigan: “We Had A Plan For It” - Eleven Warriors",
            "description": "Ryan Day said he had “an inkling” that Ohio State might lose helmet communications at Michigan, so the Buckeyes prepared for it during the week.",
            "url": "https://www.elevenwarriors.com/ohio-state-football/2025/12/160083/ryan-day-had-an-inkling-that-ohio-state-might-lose-helmet-communications-at-michigan-we-had-a-plan-for-it",
            "urlToImage": "https://www.elevenwarriors.com/sites/default/files/styles/904x490/public/c/2025/12/160083_h.jpg?itok=7oHhqHxg",
            "publishedAt": "2025-12-02T18:32:13Z",
            "content": "Ryan Day wasnt surprised when Ohio States helmet communications went out during the second half of the Buckeyes win at Michigan on Saturday. \r\nDuring his press conference on Tuesday, Day confirmed th… [+2706 chars]"
        },
        {
            "source": {
                "id": null,
                "name": "Sports Illustrated"
            },
            "author": "Madison Williams",
            "title": "Mike Tomlin Addresses Steelers’ Frustrations After Rough Loss to Bills - Sports Illustrated",
            "description": "Pittsburgh received a few costly penalties because of heightened emotions vs. Buffalo.",
            "url": "https://www.si.com/nfl/mike-tomlin-addresses-steelers-frustrations-after-rough-loss-to-bills",
            "urlToImage": "https://images2.minutemediacdn.com/image/upload/c_crop,w_5691,h_3201,x_1326,y_228/c_fill,w_1440,ar_16:9,f_auto,q_auto,g_auto/images/ImagnImages/mmsport/si/01kbg3y23abx4ppfkvjm.jpg",
            "publishedAt": "2025-12-02T18:13:04Z",
            "content": "Last Sunday's SteelersBills game was definitely a heated contest as players from both sides took some hefty penalties when tensions were high. Pittsburgh specifically had five big penalties given to … [+1593 chars]"
        },
        {
            "source": {
                "id": null,
                "name": "Bigten.org"
            },
            "author": null,
            "title": "Big Ten Conference Reveals 2025 Volleyball Postseason Honors - Big Ten Conference",
            "description": "The official athletics website for Big Ten Conference",
            "url": "https://bigten.org/wvb/article/59033/",
            "urlToImage": null,
            "publishedAt": "2025-12-02T18:02:12Z",
            "content": null
        },
        {
            "source": {
                "id": null,
                "name": "Yahoo Entertainment"
            },
            "author": "Jay Busbee",
            "title": "'It’s been a tough year': Tiger Woods shares updates on health, Ryder Cup, PGA Tour’s future - Yahoo Sports",
            "description": "With his playing days currently in limbo, Woods is turning his attention to the Tour's future schedules.",
            "url": "https://sports.yahoo.com/golf/article/its-been-a-tough-year-tiger-woods-shares-updates-on-health-ryder-cup-pga-tours-future-165432618.html",
            "urlToImage": "https://s.yimg.com/ny/api/res/1.2/WL.cxrg6WE0kqXfTCUUuNg--/YXBwaWQ9aGlnaGxhbmRlcjt3PTEyMDA7aD04NTc7Y2Y9d2VicA--/https://s.yimg.com/os/creatr-uploaded-images/2025-12/5ef5c480-cf9f-11f0-bb4b-74f6a3a2a013",
            "publishedAt": "2025-12-02T17:32:54Z",
            "content": "If its December, its time for the Hero World Challenge, the Tiger Woods-hosted 20-man tournament in the Bahamas that caps off the golf year. Woods foundation is a beneficiary of the event, and Woods … [+2925 chars]"
        },
        {
            "source": {
                "id": "fox-sports",
                "name": "Fox Sports"
            },
            "author": "Henry McKenna",
            "title": "The Big Picture: Inside that Jaxson Dart Hit and the Giants’ Profound Dysfunction - FOX Sports",
            "description": "Rookie QB Jaxson Dart's reckless play wasn't the only bad decision-making by the Giants on Monday night.",
            "url": "https://www.foxsports.com/stories/nfl/big-picture-inside-jaxson-dart-hit-giants-profound-dysfunction",
            "urlToImage": "https://a57.foxsports.com/statics.foxsports.com/www.foxsports.com/content/uploads/2025/12/1408/814/jaxson-dart-16x9-2.jpg?ve=1&tl=1",
            "publishedAt": "2025-12-02T17:24:46Z",
            "content": "Gillette Stadium (Foxborough, Mass.)  Most NFL plays are forgettable, lost in the shuffle of the 100-something set pieces throughout a game. But sometimes a play shows up on film that tells everythin… [+6193 chars]"
        },
        {
            "source": {
                "id": null,
                "name": "247Sports"
            },
            "author": "Graham Hall",
            "title": "Inside Florida's hiring of Jon Sumrall: How Urban Meyer, Danny Wuerffel and Steve Spurrier aided UF's pursuit - 247Sports",
            "description": "Urban Meyers involvement in Floridas coaching search may have been invaluable to the Gators landing Jon Sumrall",
            "url": "https://247sports.com/college/florida/article/florida-football-gators-hiring-jon-sumrall-urban-meyer-scott-stricklin-steve-spurrier-264447752/",
            "urlToImage": "https://s3media.247sports.com/Uploads/Assets/319/464/13464319.png?width=1200&height=628&crop=1.91:1&fit=cover",
            "publishedAt": "2025-12-02T17:19:34Z",
            "content": "© 2005-2025CBS INTERACTIVE ALL RIGHTS RESERVED. CBS Sports is a registered trademark of CBS Broadcasting Inc. 247Sports is a registered service mark of CBT Sports, LLC. Scout is a registered service … [+421 chars]"
        },
        {
            "source": {
                "id": null,
                "name": "MMA Fighting"
            },
            "author": "Damon Martin",
            "title": "UFC 324 start time expected to serve as permanent change under Paramount deal - MMA Fighting",
            "description": "The UFC 324 main card is set to kick off at 9 p.m. ET on Jan. 24 from Las Vegas.",
            "url": "https://www.mmafighting.com/ufc/459231/ufc-324-start-time-expected-to-serve-as-permanent-change-under-paramount-deal",
            "urlToImage": "https://platform.mmafighting.com/wp-content/uploads/sites/109/2025/10/gettyimages-2204065565.jpg?quality=90&strip=all&crop=0%2C4.8442330288091%2C100%2C78.540209844217&w=1200",
            "publishedAt": "2025-12-02T17:00:00Z",
            "content": "The UFC officially launches its broadcast partnership with Paramount on Jan. 24 and with that comes a new start time for the major numbered events.\r\nAs part of the announcement for UFC 324, which tak… [+1936 chars]"
        },
        {
            "source": {
                "id": null,
                "name": "On3.com"
            },
            "author": "Steve Wiltfong",
            "title": "Vanderbilt to flip 5-star QB Jared Curtis from Georgia - On3",
            "description": "Nashville (Tenn.) Christian five-star quarterback Jared Curtis has flipped his commitment from Georgia to Clark Lea and Vanderbilt.",
            "url": "https://www.on3.com/rivals/news/vanderbilt-to-flip-5-star-qb-jared-curtis-from-georgia/",
            "urlToImage": "https://on3static.com/uploads/dev/assets/cms/2025/12/02105047/Curtis-vandy-afi.png",
            "publishedAt": "2025-12-02T16:46:55Z",
            "content": "Rivals has learned that Nashville (Tenn.) Christian five-star quarterback Jared Curtis has informed Georgia that he will play his college football at Vanderbilt. Rivals tabs Curtis as the No. 1 passe… [+2451 chars]"
        },
        {
            "source": {
                "id": null,
                "name": "SB Nation"
            },
            "author": "Mark Schofield",
            "title": "NFL mock draft 2026: 4 QBs in first round, plus the Arch Manning dilemma - SB Nation",
            "description": "Here’s our latest NFL mock draft.",
            "url": "https://www.sbnation.com/nfl/1091884/nfl-mock-draft-2026-4-qbs-in-first-round-plus-the-arch-manning-dilemma",
            "urlToImage": "https://platform.sbnation.com/wp-content/uploads/sites/2/2025/11/gettyimages-2246770205.jpg?quality=90&strip=all&crop=0%2C1.6148689823278%2C100%2C78.534031413613&w=1200",
            "publishedAt": "2025-12-02T16:20:36Z",
            "content": "Thanksgiving has come and gone, and we are getting teams officially eliminated from playoff contention. The New York Giants were the first team eliminated following Week 12 results, and the Tennessee… [+9636 chars]"
        },
        {
            "source": {
                "id": null,
                "name": "Frontofficesports.com"
            },
            "author": "Annie Costabile",
            "title": "WNBA Proposes Cutting Team Housing, Earlier Start to Season - Front Office Sports",
            "description": "The league is proposing a seven-figure base maximum salary, but it’s coming at a cost, multiple sources told FOS.",
            "url": "http://frontofficesports.com/wnba-cba-update-housing-start-date-salary/",
            "urlToImage": "https://frontofficesports.com/wp-content/uploads/2025/12/USATSI_27120886_168416381_lowres-scaled-e1764691657306.jpg?quality=100",
            "publishedAt": "2025-12-02T16:11:27Z",
            "content": "The WNBA has proposed a seven-figure base max salary as part of a new collective bargaining agreement, but its coming at a cost. \r\nThe league has removed team housing from proposals submitted to the … [+3980 chars]"
        },
        {
            "source": {
                "id": null,
                "name": "Sports Illustrated"
            },
            "author": "Joe Nelson",
            "title": "Where Max Brosmer's dud lands among the worst-graded QB games ever - Sports Illustrated",
            "description": "Max Brosmer, thrust into the starting role as an undrafted rookie free agent, played one of the worst games in modern history in the Vikings' 26-0 loss to Seattle, according to the grades issued Monday by Pro Football Focus.",
            "url": "https://www.si.com/nfl/vikings/onsi/news/where-max-brosmer-dud-lands-among-the-worst-graded-qb-games-ever",
            "urlToImage": "https://images2.minutemediacdn.com/image/upload/c_crop,x_0,y_0,w_6000,h_3375/c_fill,w_1440,ar_1440:810,f_auto,q_auto,g_auto/images/ImagnImages/mmsport/inside_the_vikings/01kbfsry2skgszmyp7ds.jpg",
            "publishedAt": "2025-12-02T16:08:52Z",
            "content": "Max Brosmer, thrust into the starting role as an undrafted rookie free agent, played one of the worst games in modern history in the Vikings' 26-0 loss to Seattle, according to the grades issued Mond… [+2656 chars]"
        },
        {
            "source": {
                "id": null,
                "name": "Fantasypoints.com"
            },
            "author": null,
            "title": "2025 Week 14 Streaming D/STs and Kickers - Fantasy Points",
            "description": "Finding the best highly available fantasy football defenses and kickers to pick up off the waiver wire for Week 14 fantasy matchups.",
            "url": "https://www.fantasypoints.com/nfl/articles/2025/week-14-streaming-dsts-and-kickers",
            "urlToImage": "https://static.fantasypts.com/photos/ec65896db70f40bd80608581423e0bb860dc42c5/05a746a1e9516b8d72de3e801e206478e85fcc89/cover.jpg?size=1200x628&t=1764692031743",
            "publishedAt": "2025-12-02T16:00:00Z",
            "content": "When a D/ST drops a 30-burger like the Seattle Seahawks did this week, it brings a smile to my face and a tear to my eye. Theyve been a team weve pushed people to add in this article all season. Obvi… [+9841 chars]"
        },
        {
            "source": {
                "id": "the-washington-post",
                "name": "The Washington Post"
            },
            "author": "Ben Strauss",
            "title": "Winners and losers from the Lane Kiffin media circus - The Washington Post",
            "description": "College football’s hottest coaching candidate left for a rival before the playoffs. The media had a field day.",
            "url": "https://www.washingtonpost.com/sports/2025/12/02/lane-kiffin-media-winners-losers/",
            "urlToImage": "https://www.washingtonpost.com/wp-apps/imrs.php?src=https://arc-anglerfish-washpost-prod-washpost.s3.amazonaws.com/public/KITBRMXC2COQSXFC3WFLAFG7WU.jpg&w=1440",
            "publishedAt": "2025-12-02T15:53:12Z",
            "content": "Lane Kiffin, as you may have heard, has left his plush football coaching gig at Mississippi for a plusher one at LSU. Is he a winner? Who knows! Hell definitely get paid, but will he regret walking a… [+72 chars]"
        },
        {
            "source": {
                "id": null,
                "name": "Formula 1"
            },
            "author": "F1",
            "title": "Red Bull and Racing Bulls reveal 2026 driver line-ups - Formula 1",
            "description": "Red Bull and Racing Bulls have revealed their 2026 driver line-ups – with some big changes afoot…",
            "url": "https://www.formula1.com/en/latest/article/hadjar-earns-red-bull-seat-for-2026-as-rookie-lindblad-joins-lawson-at.3agyavmwcP9LJkVkRXWSEb",
            "urlToImage": "https://media.formula1.com/image/upload/t_16by9Centre/c_lfill,w_2048/q_auto/v1740000000/fom-website/2025/Red%20Bull/Red%20Bull%20%202026%20NEW%20F1%20website%20header%20templates.webp",
            "publishedAt": "2025-12-02T14:43:49Z",
            "content": "Isack Hadjar said: Im so grateful to Oracle Red Bull Racing for giving me the opportunity and trust to race at the highest level of Formula One. After all the hard work I have put in since joining th… [+1214 chars]"
        },
        {
            "source": {
                "id": null,
                "name": "detroitlions.com"
            },
            "author": null,
            "title": "Week 14 opponent: What the Cowboys are saying - Detroit Lions",
            "description": "Find out what the Dallas Cowboys are saying as they prepare for their Week 14 matchup vs. the Detroit Lions.",
            "url": "https://www.detroitlions.com/news/week-14-opponent-what-the-cowboys-are-saying-schottenheimer-williams-diggs",
            "urlToImage": "https://static.clubs.nfl.com/image/upload/t_editorial_landscape_12_desktop/lions/vaktay8wtssu4itqaafr",
            "publishedAt": "2025-12-02T12:03:27Z",
            "content": null
        },
        {
            "source": {
                "id": null,
                "name": "Lexington Herald Leader"
            },
            "author": "Jon Hale",
            "title": "Kentucky football has a new coach, but now Will Stein faces a hectic month - Lexington Herald Leader",
            "description": "Will Stein will split time with Oregon's playoff run while assembling staff, negotiating NIL and planning roster moves to stabilize Kentucky football quickly.",
            "url": "https://www.kentucky.com/sports/college/kentucky-sports/uk-football/article313307969.html",
            "urlToImage": "https://www.kentucky.com/public/latest-news/l0ds0d/picture313295130/alternates/LANDSCAPE_1140/Will%20Stein_03.JPG",
            "publishedAt": "2025-12-02T11:00:00Z",
            "content": "UK Football\r\nIt took just one day for Kentucky football to find its new coach.\r\nBut the work is just beginning in building the future of the program under Will Stein. Now, UKs new coach must build a … [+4281 chars]"
        },
        {
            "source": {
                "id": null,
                "name": "MassLive.com"
            },
            "author": "Chris Mason | cmason@masslive.com",
            "title": "How Stefon Diggs and Patriots WRs had some fun with Marcus Jones after electric TD - MassLive.com",
            "description": "Marcus Jones hasn’t played a snap on offense this season. He’s still scored three touchdowns.",
            "url": "https://www.masslive.com/patriots/2025/12/how-stefon-diggs-and-patriots-wrs-had-some-fun-with-marcus-jones-after-electric-td.html",
            "urlToImage": "https://www.masslive.com/resizer/v2/HMUEI7GIS5DCDNDOA6HYE4FEHU.jpg?auth=ab83814e010e4ea12190bc392298dad0794a7724a996e70f6a6d0c6adef4906e&width=1280&smart=true&quality=90",
            "publishedAt": "2025-12-02T11:00:00Z",
            "content": "FOXBOROUGH Marcus Jones hasnt played a snap on offense for the Patriots this season.\r\nHes still scored three touchdowns. \r\nThe electric punt returner found the end zone in the first quarter of Monday… [+2042 chars]"
        },
        {
            "source": {
                "id": null,
                "name": "cleveland.com"
            },
            "author": "Buckeye Talk Podcast, cleveland.com",
            "title": "Inside Ohio State’s 20-play drive that destroyed Michigan’s spirit - Cleveland.com",
            "description": "Buckeyes didn't just beat Michigan—they dominated them at their own game with a soul-crushing 81-yard march that lasted nearly an entire quarter and left the Wolverines demoralized.",
            "url": "https://www.cleveland.com/osu/2025/12/inside-ohio-states-20-play-drive-that-destroyed-michigans-spirit.html",
            "urlToImage": "https://www.cleveland.com/resizer/v2/2QK5ZAGHZFBCVMMZHHGXE3XMLU.JPG?auth=b320fc8f2b8b792267d9721caad83e74387722d48ca49ad1a54812b68757ceb8&width=1280&smart=true&quality=90",
            "publishedAt": "2025-12-02T06:00:00Z",
            "content": "COLUMBUS, Ohio -- Ohio State didnt just defeat Michigan on Saturdaythey broke them. And they did it with one of the most dominant, demoralizing drives youll ever see in college football.\r\nThe 20-play… [+3715 chars]"
        },
        {
            "source": {
                "id": null,
                "name": "Arizona Sports"
            },
            "author": "Kellan Olson",
            "title": "Depleted Suns steamroll Lakers to further showcase great habits - Arizona Sports",
            "description": "The Phoenix Suns are going to keep rolling teams that don't show up ready to match their energy, no matter who is available to play.",
            "url": "https://arizonasports.com/nba/phoenix-suns/suns-lakers/3604316/",
            "urlToImage": "https://arizonasports.com/wp-content/uploads/2025/12/GettyImages-2249477854-e1764653614116.jpg",
            "publishedAt": "2025-12-02T05:52:50Z",
            "content": "It wasn’t so much the feeling of déjà vu but watching a star-studded and spiritless Los Angeles Lakers squad that reinforced how far the Phoenix Suns have come, and a 125-108 complete annihilation on… [+4073 chars]"
        },
        {
            "source": {
                "id": null,
                "name": "New York Post"
            },
            "author": "Jon Heyman",
            "title": "Mets can’t settle for Devin Williams being Edwin Diaz’s replacement - New York Post",
            "description": "The Mets agreed to terms with Devin Williams, which means they now have exactly one viable right-handed reliever on their roster.",
            "url": "https://nypost.com/2025/12/01/sports/mets-cant-settle-for-devin-williams-being-edwin-diazs-replacement/",
            "urlToImage": "https://nypost.com/wp-content/uploads/sites/2/2025/12/newspress-collage-uiapr7ikn-1764650271867.jpg?quality=75&strip=all&1764632517&w=1200",
            "publishedAt": "2025-12-02T04:42:00Z",
            "content": "The Mets agreed to terms with Devin Williams, which means they now have exactly one viable right-handed reliever on their roster.\r\nThats a plus, of course. But the much better news came a few minutes… [+705 chars]"
        },
        {
            "source": {
                "id": null,
                "name": "Sports Illustrated"
            },
            "author": "Pat Forde",
            "title": "Forde-Yard Dash: Breaking Down Potential CFP Drama, Lane Kiffin’s LSU Unveiling - Sports Illustrated",
            "description": "Playoff contenders brace for a volatile week as coaching exits, league imbalances and head-to-head debates cloud the committee’s choices.",
            "url": "https://www.si.com/college-football/potential-cfp-drama-lane-kiffin-lsu-unveiling-forde-yard-dash",
            "urlToImage": "https://images2.minutemediacdn.com/image/upload/c_crop,w_3198,h_1798,x_0,y_0/c_fill,w_1440,ar_16:9,f_auto,q_auto,g_auto/images/ImagnImages/mmsport/si/01kbe7kqa5bxds5s7vkr.jpg",
            "publishedAt": "2025-12-02T01:31:40Z",
            "content": "Forty names, games, teams and minutiae making news in college football, where even a basketball coach knows the gridiron calendar is messed up. First Quarter: Shame On Everyone. Second Quarter: The S… [+11426 chars]"
        },
        {
            "source": {
                "id": null,
                "name": "Chargers.com"
            },
            "author": null,
            "title": "5 Takeaways: Justin Herbert Undergoes Successful Surgery on Left Hand - Chargers.com",
            "description": "The Chargers quarterback is considered day-to-day ahead of Monday's primetime game against the Eagles",
            "url": "https://www.chargers.com/news/justin-herbert-injury-update-hand-surgery-2025",
            "urlToImage": "https://static.clubs.nfl.com/image/upload/t_editorial_landscape_12_desktop/chargers/hi1esvz46nab8huvwcjo",
            "publishedAt": "2025-12-02T01:25:25Z",
            "content": null
        },
        {
            "source": {
                "id": null,
                "name": "Sports Illustrated"
            },
            "author": "Erick Trickel",
            "title": "Broncos Player Grades From Nail-Biting OT Win vs. Commanders - Sports Illustrated",
            "description": "The Denver Broncos' overtime win over the Washington Commanders was one of the wildest games of the year.",
            "url": "https://www.si.com/nfl/broncos/onsi/news/broncos-player-grades-commanders-ot-win-snf",
            "urlToImage": "https://images2.minutemediacdn.com/image/upload/c_crop,x_0,y_639,w_2759,h_1551/c_fill,w_1440,ar_1440:810,f_auto,q_auto,g_auto/images/ImagnImages/mmsport/mile_high_huddle/01kbdmp25mfp555pw9g7.jpg",
            "publishedAt": "2025-12-01T19:30:00Z",
            "content": "It wasnt the prettiest game, but the Denver Broncos got to 10-2 with their overtime win\r\n against the Washington Commanders. All that matters is that the Broncos got the win, keeping them in a great … [+6972 chars]"
        },
        {
            "source": {
                "id": "associated-press",
                "name": "Associated Press"
            },
            "author": "Dave Skretta",
            "title": "Andy Reid defiant as Chiefs’ playoff hopes dwindle after Thanksgiving loss to the Cowboys - AP News",
            "description": "Chiefs coach Andy Reid is defiant about his team's playoff chances despite recent setbacks. The reigning AFC champions are 6-6 with five games left. Even if they win them all, they need help to reach the postseason. The Chiefs dropped to the 10th spot in the …",
            "url": "https://apnews.com/article/kansas-city-chiefs-fc36f88babd819e2822d77c0c12af8b3",
            "urlToImage": "https://dims.apnews.com/dims4/default/39736a5/2147483647/strip/true/crop/8192x4608+0+428/resize/1440x810!/quality/90/?url=https%3A%2F%2Fassets.apnews.com%2Fd0%2F49%2Fde6e764c8e7e6f3e3cc7936f34dd%2F66bfeaec4b7b45b39465f39af0aaa66a",
            "publishedAt": "2025-12-01T19:05:00Z",
            "content": "KANSAS CITY, Mo. (AP) Kansas City Chiefs coach Andy Reid sounded downright defiant Monday when asked about his teams dwindling playoff hopes, which took a hit not only last week amid a Thanksgiving l… [+4285 chars]"
        }
    ]
}